README.txt
doc.txt
setup.cfg
setup.py
collective/__init__.py
collective.blueprint.dancing.egg-info/PKG-INFO
collective.blueprint.dancing.egg-info/SOURCES.txt
collective.blueprint.dancing.egg-info/dependency_links.txt
collective.blueprint.dancing.egg-info/entry_points.txt
collective.blueprint.dancing.egg-info/namespace_packages.txt
collective.blueprint.dancing.egg-info/not-zip-safe
collective.blueprint.dancing.egg-info/requires.txt
collective.blueprint.dancing.egg-info/top_level.txt
collective/blueprint/__init__.py
collective/blueprint/dancing/README.txt
collective/blueprint/dancing/__init__.py
collective/blueprint/dancing/configure.zcml
collective/blueprint/dancing/importsubscriber.py
collective/blueprint/dancing/importsubscriber.txt
collective/blueprint/dancing/tests.py
docs/HISTORY.txt
docs/INSTALL.txt
docs/LICENSE.GPL
docs/LICENSE.txt