Metadata-Version: 1.0
Name: collective.blueprint.dancing
Version: 0.1
Summary: collective.dancing blueprints for collective.transmogrifier pipelines
Home-page: http://www.makina-corpus.com
Author: Sylvain Boureliou
Author-email: sylvain.boureliou@makina-corpus.com
License: GPL
Keywords: plone dancing blueprints transmogrifier
Platform: UNKNOWN
Classifier: Framework :: Plone
Classifier: Framework :: Zope2
Classifier: Programming Language :: Python
Classifier: License :: OSI Approved :: GNU General Public License (GPL)
Classifier: Topic :: Software Development :: Libraries :: Application Frameworks
Classifier: Topic :: Software Development :: Libraries :: Python Modules
